Metadata-Version: 2.1
Name: datetime.datetime
Version: 0.0.1
Summary: Security Research for Dangling Packages
Home-page: UNKNOWN
License: UNKNOWN
Platform: UNKNOWN
